[
  {
    "domain": ".piesat.cn",
    "expiry": 1672451789,
    "httpOnly": false,
    "name": "engine-teamid",
    "path": "/",
    "secure": false,
    "value": "mtVVauqB2stXsnryVk6ve"
  },
  {
    "domain": ".piesat.cn",
    "expiry": 1672365386,
    "httpOnly": false,
    "name": "engine-account",
    "path": "/",
    "secure": false,
    "value": "server"
  },
  {
    "domain": ".piesat.cn",
    "expiry": 1672365386,
    "httpOnly": false,
    "name": "last-teamid",
    "path": "/",
    "secure": false,
    "value": "0"
  },
  {
    "domain": ".piesat.cn",
    "expiry": 1672365386,
    "httpOnly": false,
    "name": "engine-lang",
    "path": "/",
    "secure": false,
    "value": "zh_CN"
  },
  {
    "domain": ".piesat.cn",
    "expiry": 1672365386,
    "httpOnly": false,
    "name": "engine-token",
    "path": "/",
    "secure": false,
    "value": "1060d397ae43dabaa45877b4f618a3ae"
  },
  {
    "domain": ".engine-dev.piesat.cn",
    "httpOnly": false,
    "name": "Hm_lpvt_9c327eedfd2e580e63643703d63f0b3e",
    "path": "/",
    "secure": false,
    "value": "1672278979"
  },
  {
    "domain": ".engine-dev.piesat.cn",
    "expiry": 1703814979,
    "httpOnly": false,
    "name": "Hm_lvt_9c327eedfd2e580e63643703d63f0b3e",
    "path": "/",
    "secure": false,
    "value": "1672278979"
  }
]